agent/__init__.py
agent/ai_core.py
agent/cli.py
agent/context_manager.py
agent/error_parser.py
agent/log_monitor.py
agent/process_runner.py
agent/reporter.py
agent/sandbox_verifier.py
ai_code_repair_agent-1.1.2.dist-info/licenses/LICENSE
ai_code_repair_agent-1.1.2.dist-info/METADATA
ai_code_repair_agent-1.1.2.dist-info/WHEEL
ai_code_repair_agent-1.1.2.dist-info/entry_points.txt
ai_code_repair_agent-1.1.2.dist-info/top_level.txt
ai_code_repair_agent-1.1.2.dist-info/RECORD
