Metadata-Version: 2.4
Name: ai-code-repair-agent
Version: 1.1.2
Summary: An AI agent that automatically detects, diagnoses, and fixes bugs in Python scripts.
Author-email: Darshan S <darshansivakumar860@gmail.com>
Classifier: Programming Language :: Python :: 3
Classifier: License :: OSI Approved :: MIT License
Classifier: Operating System :: OS Independent
Requires-Python: >=3.9
License-File: LICENSE
Requires-Dist: colorama
Requires-Dist: docker
Requires-Dist: google-generativeai>=0.5.0
Requires-Dist: python-dotenv
Requires-Dist: stack-data
Requires-Dist: stdlib-list
Dynamic: license-file
